{
  "schemaVersion": 1,
  "id": "alchemycraft",
  "version": "0.0.1",
  "name": "AlchemyCraft",
  "description": "A Minecraft Mod about Alchemy, Transfiguration and much more.",
  "authors": [
    "DarkUFO"
  ],
  "contact": {
    "homepage": "",
    "sources": "https://github.com/ITDarkUFO/AlchemyCraft/",
    "curseforge": "https://www.curseforge.com/minecraft/mc-mods/alchemycraft-plus/",
    "modrinth": "https://modrinth.com/mod/alchemycraft_plus/"
  },
  "license": "GPL-3",
  "icon": "assets/alchemycraft/icon.png",
  "environment": "*",
  "entrypoints": {
    "main": [
      "net.alchemycraft.AlchemyCraft"
    ],
    "client": [
      "net.alchemycraft.AlchemyCraftClient"
    ]
  },
  "mixins": [
    "alchemycraft.mixins.json"
  ],
  "depends": {
    "fabricloader": ">=0.14.22",
    "fabric": ">=0.89.2+1.20.2",
    "minecraft": "1.20.2",
    "java": ">=17"
  }
}